pysqlsync/__init__.py
pysqlsync/base.py
pysqlsync/connection.py
pysqlsync/factory.py
pysqlsync/py.typed
pysqlsync/python_types.py
pysqlsync/resultset.py
pysqlsync/data/__init__.py
pysqlsync/data/exchange.py
pysqlsync/data/generator.py
pysqlsync/dialect/README.md
pysqlsync/dialect/__init__.py
pysqlsync/dialect/delta/__init__.py
pysqlsync/dialect/delta/data_types.py
pysqlsync/dialect/delta/dependency.py
pysqlsync/dialect/delta/engine.py
pysqlsync/dialect/delta/generator.py
pysqlsync/dialect/delta/object_types.py
pysqlsync/dialect/mssql/README.md
pysqlsync/dialect/mssql/__init__.py
pysqlsync/dialect/mssql/connection.py
pysqlsync/dialect/mssql/data_types.py
pysqlsync/dialect/mssql/dependency.py
pysqlsync/dialect/mssql/discovery.py
pysqlsync/dialect/mssql/engine.py
pysqlsync/dialect/mssql/generator.py
pysqlsync/dialect/mssql/mutation.py
pysqlsync/dialect/mssql/object_types.py
pysqlsync/dialect/mysql/__init__.py
pysqlsync/dialect/mysql/connection.py
pysqlsync/dialect/mysql/data_types.py
pysqlsync/dialect/mysql/dependency.py
pysqlsync/dialect/mysql/discovery.py
pysqlsync/dialect/mysql/engine.py
pysqlsync/dialect/mysql/generator.py
pysqlsync/dialect/mysql/mutation.py
pysqlsync/dialect/mysql/object_types.py
pysqlsync/dialect/oracle/README.md
pysqlsync/dialect/oracle/__init__.py
pysqlsync/dialect/oracle/connection.py
pysqlsync/dialect/oracle/data_types.py
pysqlsync/dialect/oracle/dependency.py
pysqlsync/dialect/oracle/discovery.py
pysqlsync/dialect/oracle/engine.py
pysqlsync/dialect/oracle/generator.py
pysqlsync/dialect/oracle/mutation.py
pysqlsync/dialect/oracle/object_types.py
pysqlsync/dialect/postgresql/__init__.py
pysqlsync/dialect/postgresql/connection.py
pysqlsync/dialect/postgresql/data_types.py
pysqlsync/dialect/postgresql/dependency.py
pysqlsync/dialect/postgresql/discovery.py
pysqlsync/dialect/postgresql/engine.py
pysqlsync/dialect/postgresql/generator.py
pysqlsync/dialect/postgresql/mutation.py
pysqlsync/dialect/postgresql/object_types.py
pysqlsync-0.8.4.dist-info/licenses/LICENSE
pysqlsync-0.8.4.dist-info/METADATA
pysqlsync-0.8.4.dist-info/WHEEL
pysqlsync-0.8.4.dist-info/top_level.txt
pysqlsync-0.8.4.dist-info/zip-safe
pysqlsync-0.8.4.dist-info/RECORD
