Metadata-Version: 2.4
Name: pysqlsync
Version: 0.8.4
Summary: Synchronize schema and large volumes of data
Author-email: Levente Hunyadi <hunyadi@gmail.com>
Maintainer-email: Levente Hunyadi <hunyadi@gmail.com>
License-Expression: MIT
Project-URL: Homepage, https://github.com/hunyadi/pysqlsync
Project-URL: Source, https://github.com/hunyadi/pysqlsync
Keywords: synchronization,sql-schema,sql-query,sql-insert,database-clients
Classifier: Development Status :: 5 - Production/Stable
Classifier: Intended Audience :: Developers
Classifier: Operating System :: OS Independent
Classifier: Programming Language :: Python :: 3
Classifier: Programming Language :: Python :: 3.9
Classifier: Programming Language :: Python :: 3.10
Classifier: Programming Language :: Python :: 3.11
Classifier: Programming Language :: Python :: 3.12
Classifier: Programming Language :: Python :: 3.13
Classifier: Programming Language :: Python :: 3.14
Classifier: Programming Language :: Python :: 3 :: Only
Classifier: Topic :: Database :: Database Engines/Servers
Classifier: Topic :: Software Development :: Code Generators
Classifier: Topic :: Software Development :: Libraries :: Python Modules
Classifier: Typing :: Typed
Requires-Python: >=3.9
License-File: LICENSE
Requires-Dist: json_strong_typing>=0.4.1
Requires-Dist: certifi>=2025.10.5; python_version < "3.10"
Requires-Dist: truststore>=0.10; python_version >= "3.10"
Requires-Dist: typing_extensions>=4.15; python_version < "3.12"
Provides-Extra: tsv
Requires-Dist: tsv2py>=0.7; extra == "tsv"
Provides-Extra: postgresql
Requires-Dist: asyncpg>=0.30; extra == "postgresql"
Provides-Extra: oracle
Requires-Dist: oracledb>=3.4; extra == "oracle"
Provides-Extra: mysql
Requires-Dist: aiomysql>=0.3; extra == "mysql"
Requires-Dist: PyMySQL[rsa]>=1.1; extra == "mysql"
Provides-Extra: mssql
Requires-Dist: pyodbc>=5.3; extra == "mssql"
Provides-Extra: snowflake
Requires-Dist: snowflake-connector-python>=3.18; extra == "snowflake"
Provides-Extra: trino
Requires-Dist: aiotrino>=0.3; extra == "trino"
Dynamic: license-file
